{
  "name": "Sprinnan",
  "icon": "medievalembroidery:sprinnan",
  "category": "medievalembroidery:plants_category",
  "pages": [
    {
      "type": "patchouli:text",
      "text": "$(l)Category:$() Herb $(br)$(l)Found In:$() Hills  $(br)$(l)Pronunciation:$() \"SPRYN-NAN\""
    },
    {
      "type": "patchouli:spotlight",
      "item": {
        "item": "medievalembroidery:sprinnan"
      },
      "text": "Sprinnan is a green herb with bright cyan ends, often found on hills. [Placeholder]"
    }
  ]
}